rightsizer/AwsRightSizer.py
rightsizer/__init__.py
rightsizer/main.py
awsrightsizer-1.1.2.dist-info/entry_points.txt
awsrightsizer-1.1.2.dist-info/LICENSE
awsrightsizer-1.1.2.dist-info/WHEEL
awsrightsizer-1.1.2.dist-info/METADATA
awsrightsizer-1.1.2.dist-info/RECORD
