Metadata-Version: 2.1
Name: awsrightsizer
Version: 1.1.2
Summary: A Python3 tool to help you determine the correct instance types to use for your running EC2/RDS instances.
Home-page: https://github.com/Gregory-Development/awsrightsizer/
License: Apache-2.0
Author: Jordan Gregory
Author-email: jordan@gregory-dev.io
Requires-Python: >=3.6,<4.0
Classifier: Development Status :: 5 - Production/Stable
Classifier: Intended Audience :: System Administrators
Classifier: License :: OSI Approved :: Apache Software License
Classifier: Programming Language :: Python :: 3
Classifier: Programming Language :: Python :: 3 :: Only
Classifier: Programming Language :: Python :: 3.6
Classifier: Programming Language :: Python :: 3.7
Requires-Dist: boto3 (>=1.9,<2.0)
Requires-Dist: click (>=7.0,<8.0)
Project-URL: Documentation, http://awsrightsizer.readthedocs.io
Project-URL: Repository, https://github.com/Gregory-Development/awsrightsizer/
